ipyturtle3/__init__.py
ipyturtle3/ipyturtle3.py
ipyturtle3-0.1.4.dist-info/LICENSE
ipyturtle3-0.1.4.dist-info/METADATA
ipyturtle3-0.1.4.dist-info/WHEEL
ipyturtle3-0.1.4.dist-info/top_level.txt
ipyturtle3-0.1.4.dist-info/RECORD
