Metadata-Version: 2.1
Name: ipyturtle3
Version: 0.1.4
Summary: Turtle graphics based on ipycanvas which can run on jupyter lab/notebook/vscode. 
Home-page: https://github.com/williamnavaraj/ipyturtle3.git
Author: William Navaraj
Author-email: williamnavaraj@gmail.com
License: Apache 2.0
Platform: UNKNOWN
Classifier: Development Status :: 3 - Alpha
Classifier: Intended Audience :: Education
Classifier: License :: OSI Approved :: Apache Software License
Classifier: Programming Language :: Python :: 3
Classifier: Programming Language :: Python :: 3.6
Classifier: Programming Language :: Python :: 3.7
Classifier: Programming Language :: Python :: 3.8
Classifier: Programming Language :: Python :: 3.9
Classifier: Programming Language :: Python :: 3.10
Requires-Dist: ipycanvas
Requires-Dist: webcolors
